{
  "_note": "R-18 地の文の合成素材（ランダム表記）。既定 OFF の R18 トグルが ON のときだけ使われる。成体のつがいのみ（mating）に差し込まれ、子供には一切回らない。TextDB.compose(grammar, rng, fields) が templates の {slot} を同名リストからランダムに埋め、最後に {name}/{other} を format する。スロット語に {} を入れないこと。露骨さは各リストを編集して調整可。削除すれば通常文面に戻る。編集後は test_dialogue.gd で検証。",

  "mating_explicit": {
    "templates": [
      "寝床で {name} が{posture}、{act}{intens}。{coda}",
      "{name} は{posture}、{act}{intens}。{coda}",
      "{name} が{act}{intens}、{coda}",
      "藁の上、{name} は{posture}たまま{coda}",
      "寝床の奥で {name} が{soliloquy}"
    ],
    "posture": [
      "雄に組み敷かれ",
      "自ら腰を落として咥え込み",
      "四つん這いで尻を突き出し",
      "相手を押し倒して跨り",
      "壁に手をついて尻を掲げ",
      "汗だくで脚を絡め"
    ],
    "act": [
      "濡れた音を立てて突き上げられ",
      "奥まで深々と貫かれ",
      "腰を打ちつけ合い",
      "太いのを根元まで呑み込み",
      "がつがつと腰を振り立て",
      "繋がったまま揺さぶられ"
    ],
    "intens": [
      "何度も",
      "激しく",
      "容赦なく",
      "休みなく",
      "獣じみた勢いで",
      ""
    ],
    "coda": [
      "けものじみた嬌声をあげた。",
      "涎を垂らして果てた。",
      "種をたっぷり腹に注がれた。",
      "奥で受け止めて痙攣した。",
      "汗まみれで絶頂した。",
      "満たされた長い唸りを漏らした。"
    ],
    "soliloquy": [
      "雄の精を搾り取るように腰を使っている。",
      "繋がったまま二度三度と果てている。",
      "太いのに貫かれて白目を剥いている。",
      "腹がはち切れるまでと種をねだっている。"
    ]
  },

  "mating_explicit_pair": {
    "templates": [
      "寝床で {name} と {other} が{pair_posture}、{pair_act}{intens}。{coda}",
      "{name} が {other} を{mount}、{pair_act}{intens}。{coda}",
      "{name} と {other} が繋がったまま{pair_posture}、{coda}"
    ],
    "pair_posture": [
      "汗まみれでもつれ合い",
      "互いの腰を掴み合い",
      "息を荒げて絡み合い",
      "藁を蹴散らして組み合い"
    ],
    "mount": [
      "組み敷いて",
      "押し倒して",
      "四つん這いにさせて",
      "跨らせて"
    ],
    "pair_act": [
      "濡れた音を響かせて腰を打ちつけ",
      "奥まで深々と貫いて",
      "繋がったまま激しく揺さぶり合い",
      "がつがつと突き上げ"
    ],
    "intens": [
      "何度も",
      "激しく",
      "容赦なく",
      "夜通し",
      ""
    ],
    "coda": [
      "二匹そろって獣じみた声をあげた。",
      "{name} の腹にたっぷり種が注がれた。",
      "汗だくで折り重なって果てた。",
      "繋がったまま二度三度と痙攣した。",
      "満たされた唸りが寝床に満ちた。"
    ]
  }
}
